JavaMianshiBiji/README.md
JavaMianshiBiji/__init__.py
JavaMianshiBiji/__main__.py
JavaMianshiBiji/file.epub
JavaMianshiBiji/index.html
JavaMianshiBiji/css/__init__.py
JavaMianshiBiji/css/annotations.css
JavaMianshiBiji/css/main.css
JavaMianshiBiji/css/normalize.css
JavaMianshiBiji/css/popup.css
JavaMianshiBiji/font/__init__.py
JavaMianshiBiji/font/fontello.eot
JavaMianshiBiji/font/fontello.svg
JavaMianshiBiji/font/fontello.ttf
JavaMianshiBiji/font/fontello.woff
JavaMianshiBiji/img/__init__.py
JavaMianshiBiji/img/annotator-glyph-sprite.png
JavaMianshiBiji/img/annotator-icon-sprite.png
JavaMianshiBiji/img/apple-touch-icon.png
JavaMianshiBiji/img/cancelfullscreen.png
JavaMianshiBiji/img/close.png
JavaMianshiBiji/img/fullscreen.png
JavaMianshiBiji/img/loader.gif
JavaMianshiBiji/img/menu-icon.png
JavaMianshiBiji/img/save.png
JavaMianshiBiji/img/saved.png
JavaMianshiBiji/img/settings-s.png
JavaMianshiBiji/img/settings.png
JavaMianshiBiji/img/star.png
JavaMianshiBiji/js/__init__.py
JavaMianshiBiji/js/epub.js
JavaMianshiBiji/js/epub.min.js
JavaMianshiBiji/js/epub.min.map
JavaMianshiBiji/js/hooks.min.js
JavaMianshiBiji/js/hooks.min.map
JavaMianshiBiji/js/reader.js
JavaMianshiBiji/js/reader.js.map
JavaMianshiBiji/js/reader.min.js
JavaMianshiBiji/js/reader.min.map
JavaMianshiBiji/js/hooks/__init__.py
JavaMianshiBiji/js/hooks/extensions/__init__.py
JavaMianshiBiji/js/hooks/extensions/highlight.js
JavaMianshiBiji/js/libs/__init__.py
JavaMianshiBiji/js/libs/jquery.min.js
JavaMianshiBiji/js/libs/localforage.min.js
JavaMianshiBiji/js/libs/screenfull.js
JavaMianshiBiji/js/libs/screenfull.min.js
JavaMianshiBiji/js/libs/zip.min.js
JavaMianshiBiji/js/plugins/__init__.py
JavaMianshiBiji/js/plugins/hypothesis.js
JavaMianshiBiji/js/plugins/search.js
java_mianshi_biji-2024.3.3.0.dist-info/METADATA
java_mianshi_biji-2024.3.3.0.dist-info/WHEEL
java_mianshi_biji-2024.3.3.0.dist-info/entry_points.txt
java_mianshi_biji-2024.3.3.0.dist-info/top_level.txt
java_mianshi_biji-2024.3.3.0.dist-info/RECORD
